lemity/__init__.py
lemity/app.py
lemity/converter.py
lemity/main.py
lemity/static/video-js.css
lemity/static/video.min.js
lemity/templates/index.html
lemity/templates/play.html
lemity-2019.6.1.dist-info/METADATA
lemity-2019.6.1.dist-info/WHEEL
lemity-2019.6.1.dist-info/entry_points.txt
lemity-2019.6.1.dist-info/top_level.txt
lemity-2019.6.1.dist-info/RECORD
